deputy/__init__.py
deputy/__main__.py
deputy/util.py
deputy/magnum/__init__.py
deputy/magnum/cli.py
deputy/magnum/magnum.py
deputy/serialmon/__init__.py
deputy/serialmon/cli.py
deputy/serialmon/serialmon.py
deputy/serialmon/term.py
deputy-0.0.1.dist-info/LICENSE
deputy-0.0.1.dist-info/METADATA
deputy-0.0.1.dist-info/WHEEL
deputy-0.0.1.dist-info/entry_points.txt
deputy-0.0.1.dist-info/top_level.txt
deputy-0.0.1.dist-info/RECORD
